.codeclimate.yml
.landscape.yml
.travis.yml
AUTHORS
ChangeLog
LICENSE-2.0.txt
README.rst
conftest.py
requirements.txt
setup.cfg
setup.py
.circleci/config.yml
conda/dev-environment.yml
conda/meta.yaml
docs/Makefile
docs/conf.py
docs/index.rst
docs/readme.rst
nchash/__init__.py
nchash/nchash.py
nchash.egg-info/PKG-INFO
nchash.egg-info/SOURCES.txt
nchash.egg-info/dependency_links.txt
nchash.egg-info/entry_points.txt
nchash.egg-info/not-zip-safe
nchash.egg-info/pbr.json
nchash.egg-info/requires.txt
nchash.egg-info/top_level.txt
test/.empty
test/test_nchash.py
test/utils.py